dagster_slurm/__init__.py
dagster_slurm/config/__init__.py
dagster_slurm/config/environment.py
dagster_slurm/config/runtime.py
dagster_slurm/helpers/__init__.py
dagster_slurm/helpers/env_packaging.py
dagster_slurm/helpers/message_readers.py
dagster_slurm/helpers/metrics.py
dagster_slurm/helpers/ssh_helpers.py
dagster_slurm/helpers/ssh_pool.py
dagster_slurm/launchers/__init__.py
dagster_slurm/launchers/base.py
dagster_slurm/launchers/ray.py
dagster_slurm/launchers/script.py
dagster_slurm/launchers/spark.py
dagster_slurm/managers/__init__.py
dagster_slurm/managers/hetjob.py
dagster_slurm/pipes_clients/__init__.py
dagster_slurm/pipes_clients/local_pipes_client.py
dagster_slurm/pipes_clients/slurm_pipes_client.py
dagster_slurm/py.typed
dagster_slurm/resources/__init__.py
dagster_slurm/resources/compute.py
dagster_slurm/resources/session.py
dagster_slurm/resources/slurm.py
dagster_slurm/resources/ssh.py
dagster_slurm/runners/__init__.py
dagster_slurm/runners/base.py
dagster_slurm/runners/local_runner.py
dagster_slurm-1.9.0.dist-info/WHEEL
dagster_slurm-1.9.0.dist-info/METADATA
dagster_slurm-1.9.0.dist-info/RECORD
