Metadata-Version: 2.3
Name: dagster-slurm
Version: 1.9.0
Summary: dagster integration with slurm
Keywords: dagster,slurm,hpc,workflow-orchestration,ray,feray
Author: geoheil
Author-email: geoheil <georg.heiler@ascii.ac.at>
License: Apache-2.0
Classifier: Development Status :: 3 - Alpha
Classifier: Intended Audience :: Developers
Classifier: License :: OSI Approved :: Apache Software License
Classifier: Operating System :: OS Independent
Classifier: Programming Language :: Python :: 3
Classifier: Programming Language :: Python :: 3.11
Classifier: Programming Language :: Python :: 3.12
Classifier: Topic :: System :: Distributed Computing
Classifier: Topic :: Software Development :: Libraries :: Python Modules
Requires-Dist: dagster>=1.11.7
Requires-Dist: dagster-pipes>=1.11.7
Requires-Dist: loguru>=0.7
Requires-Dist: pexpect~=4.9.0
Requires-Dist: ray>=2.48.0 ; extra == 'ray'
Requires-Python: >=3.12, <3.13
Project-URL: Bug Reports, https://github.com/ascii-supply-networks/dagster-slurm/issues
Project-URL: Documentation, https://dagster-slurm.geoheil.com/docs/intro
Project-URL: Homepage, https://dagster-slurm.geoheil.com/
Project-URL: Repository, https://github.com/ascii-supply-networks/dagster-slurm
Provides-Extra: ray
